sconce/DirLinSCMS.py
sconce/DirLinSCMS_RayFunc.py
sconce/DirSCMS.py
sconce/DirSCMS_RayFunc.py
sconce/EucSCMS.py
sconce/EucSCMS_RayFunc.py
sconce/FilaAttr.py
sconce/__init__.py
sconce/utils.py
sconce_scms-0.1.2.dist-info/LICENSE
sconce_scms-0.1.2.dist-info/METADATA
sconce_scms-0.1.2.dist-info/WHEEL
sconce_scms-0.1.2.dist-info/top_level.txt
sconce_scms-0.1.2.dist-info/RECORD
