Metadata-Version: 2.1
Name: sconce-scms
Version: 0.1.2
Summary: Spherical and Conic Cosmic Web Finders with Extended SCMS Algorithms
Home-page: https://github.com/zhangyk8/sconce-scms
Author: Yikun Zhang
Author-email: yikunzhang@foxmail.com
Classifier: Programming Language :: Python :: 3
Classifier: License :: OSI Approved :: MIT License
Classifier: Operating System :: OS Independent
Requires-Python: >=3.6
License-File: LICENSE
Requires-Dist: numpy
Requires-Dist: scipy
Requires-Dist: ray[default]
Requires-Dist: scikit-learn
